todo/__init__.py
todo/admin.py
todo/authentication.py
todo/caldav.py
todo/models.py
todo/parsers.py
todo/response.py
todo/signals.py
todo/urls.py
todo/version.py
todo/views.py
todo/migrations/0001_initial.py
todo/migrations/__init__.py
todo/standalone/__init__.py
todo/standalone/asgi.py
todo/standalone/manage.py
todo/standalone/settings.py
todo/standalone/urls.py
todo/standalone/wsgi.py
CalDavFramework-0.1.dev0.dist-info/LICENSE
CalDavFramework-0.1.dev0.dist-info/METADATA
CalDavFramework-0.1.dev0.dist-info/WHEEL
CalDavFramework-0.1.dev0.dist-info/entry_points.txt
CalDavFramework-0.1.dev0.dist-info/top_level.txt
CalDavFramework-0.1.dev0.dist-info/RECORD
